napari_elementary_numpy_operations/__init__.py
napari_elementary_numpy_operations/_version.py
napari_elementary_numpy_operations/napari_numpy.py
napari_elementary_numpy_operations-0.0.5.dist-info/LICENSE
napari_elementary_numpy_operations-0.0.5.dist-info/METADATA
napari_elementary_numpy_operations-0.0.5.dist-info/WHEEL
napari_elementary_numpy_operations-0.0.5.dist-info/entry_points.txt
napari_elementary_numpy_operations-0.0.5.dist-info/top_level.txt
napari_elementary_numpy_operations-0.0.5.dist-info/RECORD
