Metadata-Version: 2.1
Name: napari-elementary-numpy-operations
Version: 0.0.5
Summary: A napari plugin covers elementary numpy operations like swap axes, flip, sqeeze an array or rotate an arrays by 90° steps
Home-page: https://github.com/MBPhys/napari-elementary-numpy-operations
Author: Marc Boucsein, Robin Koch
License: BSD-3
Platform: UNKNOWN
Classifier: Development Status :: 4 - Beta
Classifier: Intended Audience :: Developers
Classifier: Framework :: napari
Classifier: Topic :: Software Development :: Testing
Classifier: Programming Language :: Python
Classifier: Programming Language :: Python :: 3
Classifier: Programming Language :: Python :: 3.7
Classifier: Programming Language :: Python :: 3.8
Classifier: Programming Language :: Python :: 3.9
Classifier: Operating System :: OS Independent
Classifier: License :: OSI Approved :: BSD License
Requires-Python: >=3.7
License-File: LICENSE
Requires-Dist: napari-plugin-engine (>=0.1.4)
Requires-Dist: numpy
Requires-Dist: qtpy
Requires-Dist: superqt
